Workbook

Sheet Guía
C1: MLR CONSULTORES
C2: Cómo usar este libro
C3: <Empresa> · <Mes Año>
A5: Léelo una vez. Después solo abres el Resumen y atiendes los renglones que no dicen "Conciliado".
B7: 1 | C7: Abre el Resumen. Si la pregunta 2 dice "Todo conciliado" y las diferencias de la 1 y la 3 son cero, el mes cuadró.
B9: 2 | C9: Si no, ve a la hoja Conciliación y filtra la columna Estatus. Trabaja primero "No identificado" y después "Conciliado (revisar)".
B11: 3 | C11: La columna Observación explica cada renglón. Corrige en Odoo o pide el CFDI; en la siguiente corrida el renglón cambia solo.
B13: 4 | C13: Revisa el Previo, captura lo que está en azul claro (nómina, saldo a favor) y envíalo al cliente.
C16: Qué hay en cada hoja
C17: Resumen: seis preguntas del mes con su respuesta.
C18: Conciliación: banco, Odoo y CFDI en una sola hoja, con el IVA y las retenciones de cada movimiento.
C19: Desglose fiscal: IVA y retenciones del mes por tipo de retención, y el cuadre del flujo contra el banco.
C20: Previo: el cálculo que se envía al cliente.
C21: Facturas vs Odoo: cada CFDI del mes contra su registro en Odoo.
C22: Impuestos vs Odoo: el IVA de las cuentas 208.01 y 118.01 de Odoo contra la conciliación, factura por factura.
C23: Estado de cuenta: los movimientos del PDF con la carátula a la derecha.
C24: Auxiliar Odoo: el auxiliar de bancos tal como se exportó.
C25: Reglas: tolerancias, estatus y tabla de retenciones.
C27: Colores por tipo de retención (solo renglones conciliados)
C28: Honorarios
... C40: Fuentes: estado de cuenta del banco del mes (PDF o Excel); de Odoo, el auxiliar del diario, las facturas del mes y el libro mayor de las cuentas de IVA en flujo; acumulado de XML de Mi Admin con sus complementos de pago.

Sheet Resumen
C1: MLR CONSULTORES
C2: ¿Cuadró el mes?
C3: <Empresa> · <Mes Año>
A5: Cuenta <número> · Periodo <dd/mm/aaaa> al <dd/mm/aaaa>. Todo se calcula solo a partir de las hojas del libro.
B7: 1 | C7: ¿El PDF quedó bien leído? | F7: 2 | G7: ¿Cómo quedó cada movimiento?
C8: =IF(AND('Estado de cuenta'!L27=0,'Estado de cuenta'!M27=0),"Sí. Saldos y número de movimientos cuadran con la carátula.","No. Revisa la hoja Estado de cuenta.") | G8: =IF(COUNTIFS(Conciliación!$AL$8:$AL$114,1,Conciliación!$AD$8:$AD$114,"No identificado")+COUNTIFS(Conciliación!$AL$8:$AL$114,1,Conciliación!$AD$8:$AD$114,"Conciliado (revisar)")=0,"Todo conciliado.","Hay "&COUNTIFS(Conciliación!$AL$8:$AL$114,1,Conciliación!$AD$8:$AD$114,"No identificado")&" no identificados y "&COUNTIFS(Conciliación!$AL$8:$AL$114,1,Conciliación!$AD$8:$AD$114,"Conciliado (revisar)")&" por revisar.")
C9: Saldo inicial | D9: ='Estado de cuenta'!L16 | G9: Conciliado | H9: =COUNTIFS(Conciliación!$AL$8:$AL$114,1,Conciliación!$AD$8:$AD$114,"Conciliado")
C10: (+) Abonos | D10: ='Estado de cuenta'!L24 | G10: Conciliado (validar) | H10: =COUNTIFS(Conciliación!$AL$8:$AL$114,1,Conciliación!$AD$8:$AD$114,"Conciliado (validar)")
C11: (-) Cargos | D11: ='Estado de cuenta'!L25 | G11: Conciliado (revisar) | H11: =COUNTIFS(Conciliación!$AL$8:$AL$114,1,Conciliación!$AD$8:$AD$114,"Conciliado (revisar)")
C12: Saldo final calculado | D12: ='Estado de cuenta'!L26 | G12: No identificado | H12: =COUNTIFS(Conciliación!$AL$8:$AL$114,1,Conciliación!$AD$8:$AD$114,"No identificado")
C13: Saldo final de la carátula | D13: ='Estado de cuenta'!L19 | G13: Total de partidas | H13: =SUM(Conciliación!$AL$8:$AL$114)
C14: Diferencia | D14: ='Estado de cuenta'!L27 | G14: Saldo final Odoo vs banco | H14: ='Auxiliar Odoo'!J10
B17: 3 | C17: ¿Cuánto dinero hay en cada estatus? | F17: 4 | G17: ¿Qué alertas fiscales hay?
C18: ="Importe aplicado a cada estatus, cobros y pagos juntos." | G18: =IF(COUNTIF(Conciliación!$AE$8:$AE$114,"*Alerta*")=0,"Ninguna.","Hay "&COUNTIF(Conciliación!$AE$8:$AE$114,"*Alerta*")&" renglones con alerta: revísalos antes de cerrar.")
C19: Conciliado | D19: =SUMIFS(Conciliación!$W$8:$W$114,Conciliación!$AD$8:$AD$114,"Conciliado") | G19: PUE cobradas en otro mes o en parcialidades | H19: =COUNTIF(Conciliación!$AE$8:$AE$114,"*PUE*")
C20: Conciliado (validar) | D20: =SUMIFS(Conciliación!$W$8:$W$114,Conciliación!$AD$8:$AD$114,"Conciliado (validar)") | G20: Posibles retenciones omitidas | H20: =COUNTIF(Conciliación!$AE$8:$AE$114,"*omitida*")
C21: Conciliado (revisar) | D21: =SUMIFS(Conciliación!$W$8:$W$114,Conciliación!$AD$8:$AD$114,"Conciliado (revisar)") | G21: Pagos a "COMISIONES" sin CFDI | H21: =SUMIFS(Conciliación!$W$8:$W$114,Conciliación!$AE$8:$AE$114,"*COMISIONES*")
C22: No identificado | D22: =SUMIFS(Conciliación!$W$8:$W$114,Conciliación!$AD$8:$AD$114,"No identificado") | G22: Renglones sin contacto en Odoo | H22: =COUNTIFS(Conciliación!$AL$8:$AL$114,1,Conciliación!$F$8:$F$114,"?*",Conciliación!$I$8:$I$114,"")
C23: Flujo explicado, diferencia cobros | D23: ='Desglose fiscal'!B43
C24: Flujo explicado, diferencia pagos | D24: ='Desglose fiscal'!C43
B27: 5 | C27: ¿Cuánto se paga este mes? | F27: 6 | G27: ¿Odoo dice lo mismo que el SAT y el banco?
C28: ="Total a pagar según el previo: $"&TEXT(Previo!F36,"#,##0") | G28: =IF(COUNTIF('Facturas vs Odoo'!$L$8:$L$94,"Conciliado")=COUNTA('Facturas vs Odoo'!$L$8:$L$94),"Las facturas del mes cuadran con Odoo.","Hay "&(COUNTA('Facturas vs Odoo'!$L$8:$L$94)-COUNTIF('Facturas vs Odoo'!$L$8:$L$94,"Conciliado"))&" facturas por atender en Odoo.")
C29: ISR retenido | D29: =Previo!F16 | G29: Facturas conciliadas con Odoo | H29: =COUNTIF('Facturas vs Odoo'!$L$8:$L$94,"Conciliado")
C30: ISR persona moral | D30: =Previo!F22 | G30: Facturas por revisar o no identificadas | H30: =COUNTA('Facturas vs Odoo'!$L$8:$L$94)-COUNTIF('Facturas vs Odoo'!$L$8:$L$94,"Conciliado")
C31: IVA por pagar | D31: =Previo!F28 | G31: IVA trasladado: Odoo menos conciliación | H31: ='Impuestos vs Odoo'!G10
C32: IVA a favor del mes | D32: =Previo!F29 | G32: IVA acreditable: Odoo menos conciliación | H32: ='Impuestos vs Odoo'!G9
C33: IVA retenido | D33: =Previo!F33 | G33: Reversiones de flujo en Odoo | H33: =COUNTIF('Impuestos vs Odoo'!$J$16:$J$95,"*reversión*")
C36: Colores del estatus
C37: Conciliado | D37: Banco, Odoo y CFDI coinciden dentro de las tolerancias. Incluye comisiones, impuestos y nómina, que no requieren CFDI individual.
C38: Conciliado (validar) | D38: Un pago que cubre varias facturas, varias facturas en un pago, o un cobro parcial de una factura.
C39: Conciliado (revisar) | D39: Tiene pareja, pero la diferencia pasa de la tolerancia de importe o el desfase pasa de la tolerancia de días.
C40: No identificado | D40: Está en el banco y no en Odoo, está en Odoo y no en el banco, o no tiene CFDI que lo respalde.

Sheet Conciliación
C1: MLR CONSULTORES
C2: Conciliación: banco, Odoo y CFDI
C3: <Empresa> · <Mes Año>
A5: Cada renglón es una factura que ampara un movimiento. Si un depósito paga tres facturas, la partida tiene tres renglones y el importe del banco aparece solo en el primero.
A6: BANCO | F6: ODOO | N6: CFDI | AD6: RESULTADO
A7: Partida | B7: Fecha banco | C7: Concepto banco | D7: Cargo banco | E7: Abono banco | F7: Renglón Odoo | G7: Fecha Odoo | H7: Asiento Odoo | I7: Contacto en Odoo | J7: Cargo Odoo | K7: Abono Odoo | L7: Dif. banco vs Odoo | M7: Días banco vs Odoo | N7: Enlace | O7: UUID | P7: Folio | Q7: Fecha CFDI | R7: Cliente o proveedor del CFDI | S7: RFC | T7: Método | U7: Tipo de retención | V7: Total CFDI | W7: Importe aplicado | X7: Base | Y7: IVA | Z7: IVA retenido | AA7: ISR retenido | AB7: Días banco vs pago CFDI | AC7: Dif. movimiento vs CFDI | AD7: Estatus | AE7: Observación | AF7: Base CFDI | AG7: IVA CFDI | AH7: IVA ret. CFDI | AI7: ISR ret. CFDI | AJ7: Tipo | AK7: Excedente | AL7: Primera
L8: =IF(OR(F8="",AL8=0),"",(D8+E8)-(J8+K8)) | M8: =IF(OR(F8="",AL8=0,B8=""),"",G8-B8) | X8: =IF(OR(V8="",V8=0),0,ROUND(W8/V8*AF8,2)) | Y8: =IF(OR(V8="",V8=0),0,ROUND(W8/V8*AG8,2)) | Z8: =IF(OR(V8="",V8=0),0,ROUND(W8/V8*AH8,2)) | AA8: =IF(OR(V8="",V8=0),0,ROUND(W8/V8*AI8,2)) | AC8: =ROUND(SUMIF($A$8:$A$114,A8,$D$8:$D$114)+SUMIF($A$8:$A$114,A8,$E$8:$E$114)-SUMIF($A$8:$A$114,A8,$W$8:$W$114),2) | AD8: =IF(OR((SUMIF($A$8:$A$114,A8,$D$8:$D$114)+SUMIF($A$8:$A$114,A8,$E$8:$E$114))=0,COUNTIFS($A$8:$A$114,A8,$F$8:$F$114,"?*")=0,N8="Sin CFDI"),"No identificado",IF(OR(ABS(SUMIF($A$8:$A$114,A8,$L$8:$L$114))>Reglas!$C$7,ABS(SUMIF($A$8:$A$114,A8,$M$8:$M$114))>Reglas!$C$8,ABS(AC8)>Reglas!$C$7,ABS(N(AB8))>Reglas!$C$8),"Conciliado (revisar)",IF(OR(N8="Varios CFDI",N8="Parcial"),"Conciliado (validar)","Conciliado"))) | AK8: =IF(AL8=1,ROUND(SUMIF($A$8:$A$114,A8,$D$8:$D$114)+SUMIF($A$8:$A$114,A8,$E$8:$E$114)-SUMIF($A$8:$A$114,A8,$W$8:$W$114),2),0)
L9: =IF(OR(F9="",AL9=0),"",(D9+E9)-(J9+K9)) | M9: =IF(OR(F9="",AL9=0,B9=""),"",G9-B9) | X9: =IF(OR(V9="",V9=0),0,ROUND(W9/V9*AF9,2)) | Y9: =IF(OR(V9="",V9=0),0,ROUND(W9/V9*AG9,2)) | Z9: =IF(OR(V9="",V9=0),0,ROUND(W9/V9*AH9,2)) | AA9: =IF(OR(V9="",V9=0),0,ROUND(W9/V9*AI9,2)) | AC9: =ROUND(SUMIF($A$8:$A$114,A9,$D$8:$D$114)+SUMIF($A$8:$A$114,A9,$E$8:$E$114)-SUMIF($A$8:$A$114,A9,$W$8:$W$114),2) | AD9: =IF(OR((SUMIF($A$8:$A$114,A9,$D$8:$D$114)+SUMIF($A$8:$A$114,A9,$E$8:$E$114))=0,COUNTIFS($A$8:$A$114,A9,$F$8:$F$114,"?*")=0,N9="Sin CFDI"),"No identificado",IF(OR(ABS(SUMIF($A$8:$A$114,A9,$L$8:$L$114))>Reglas!$C$7,ABS(SUMIF($A$8:$A$114,A9,$M$8:$M$114))>Reglas!$C$8,ABS(AC9)>Reglas!$C$7,ABS(N(AB9))>Reglas!$C$8),"Conciliado (revisar)",IF(OR(N9="Varios CFDI",N9="Parcial"),"Conciliado (validar)","Conciliado"))) | AK9: =IF(AL9=1,ROUND(SUMIF($A$8:$A$114,A9,$D$8:$D$114)+SUMIF($A$8:$A$114,A9,$E$8:$E$114)-SUMIF($A$8:$A$114,A9,$W$8:$W$114),2),0)
L10: =IF(OR(F10="",AL10=0),"",(D10+E10)-(J10+K10)) | M10: =IF(OR(F10="",AL10=0,B10=""),"",G10-B10) | X10: =IF(OR(V10="",V10=0),0,ROUND(W10/V10*AF10,2)) | Y10: =IF(OR(V10="",V10=0),0,ROUND(W10/V10*AG10,2)) | Z10: =IF(OR(V10="",V10=0),0,ROUND(W10/V10*AH10,2)) | AA10: =IF(OR(V10="",V10=0),0,ROUND(W10/V10*AI10,2)) | AC10: =ROUND(SUMIF($A$8:$A$114,A10,$D$8:$D$114)+SUMIF($A$8:$A$114,A10,$E$8:$E$114)-SUMIF($A$8:$A$114,A10,$W$8:$W$114),2) | AD10: =IF(OR((SUMIF($A$8:$A$114,A10,$D$8:$D$114)+SUMIF($A$8:$A$114,A10,$E$8:$E$114))=0,COUNTIFS($A$8:$A$114,A10,$F$8:$F$114,"?*")=0,N10="Sin CFDI"),"No identificado",IF(OR(ABS(SUMIF($A$8:$A$114,A10,$L$8:$L$114))>Reglas!$C$7,ABS(SUMIF($A$8:$A$114,A10,$M$8:$M$114))>Reglas!$C$8,ABS(AC10)>Reglas!$C$7,ABS(N(AB10))>Reglas!$C$8),"Conciliado (revisar)",IF(OR(N10="Varios CFDI",N10="Parcial"),"Conciliado (validar)","Conciliado"))) | AK10: =IF(AL10=1,ROUND(SUMIF($A$8:$A$114,A10,$D$8:$D$114)+SUMIF($A$8:$A$114,A10,$E$8:$E$114)-SUMIF($A$8:$A$114,A10,$W$8:$W$114),2),0)
L11: =IF(OR(F11="",AL11=0),"",(D11+E11)-(J11+K11)) | M11: =IF(OR(F11="",AL11=0,B11=""),"",G11-B11) | X11: =IF(OR(V11="",V11=0),0,ROUND(W11/V11*AF11,2)) | Y11: =IF(OR(V11="",V11=0),0,ROUND(W11/V11*AG11,2)) | Z11: =IF(OR(V11="",V11=0),0,ROUND(W11/V11*AH11,2)) | AA11: =IF(OR(V11="",V11=0),0,ROUND(W11/V11*AI11,2)) | AC11: =ROUND(SUMIF($A$8:$A$114,A11,$D$8:$D$114)+SUMIF($A$8:$A$114,A11,$E$8:$E$114)-SUMIF($A$8:$A$114,A11,$W$8:$W$114),2) | AD11: =IF(OR((SUMIF($A$8:$A$114,A11,$D$8:$D$114)+SUMIF($A$8:$A$114,A11,$E$8:$E$114))=0,COUNTIFS($A$8:$A$114,A11,$F$8:$F$114,"?*")=0,N11="Sin CFDI"),"No identificado",IF(OR(ABS(SUMIF($A$8:$A$114,A11,$L$8:$L$114))>Reglas!$C$7,ABS(SUMIF($A$8:$A$114,A11,$M$8:$M$114))>Reglas!$C$8,ABS(AC11)>Reglas!$C$7,ABS(N(AB11))>Reglas!$C$8),"Conciliado (revisar)",IF(OR(N11="Varios CFDI",N11="Parcial"),"Conciliado (validar)","Conciliado"))) | AK11: =IF(AL11=1,ROUND(SUMIF($A$8:$A$114,A11,$D$8:$D$114)+SUMIF($A$8:$A$114,A11,$E$8:$E$114)-SUMIF($A$8:$A$114,A11,$W$8:$W$114),2),0)
L12: =IF(OR(F12="",AL12=0),"",(D12+E12)-(J12+K12)) | M12: =IF(OR(F12="",AL12=0,B12=""),"",G12-B12) | X12: =IF(OR(V12="",V12=0),0,ROUND(W12/V12*AF12,2)) | Y12: =IF(OR(V12="",V12=0),0,ROUND(W12/V12*AG12,2)) | Z12: =IF(OR(V12="",V12=0),0,ROUND(W12/V12*AH12,2)) | AA12: =IF(OR(V12="",V12=0),0,ROUND(W12/V12*AI12,2)) | AC12: =ROUND(SUMIF($A$8:$A$114,A12,$D$8:$D$114)+SUMIF($A$8:$A$114,A12,$E$8:$E$114)-SUMIF($A$8:$A$114,A12,$W$8:$W$114),2) | AD12: =IF(OR((SUMIF($A$8:$A$114,A12,$D$8:$D$114)+SUMIF($A$8:$A$114,A12,$E$8:$E$114))=0,COUNTIFS($A$8:$A$114,A12,$F$8:$F$114,"?*")=0,N12="Sin CFDI"),"No identificado",IF(OR(ABS(SUMIF($A$8:$A$114,A12,$L$8:$L$114))>Reglas!$C$7,ABS(SUMIF($A$8:$A$114,A12,$M$8:$M$114))>Reglas!$C$8,ABS(AC12)>Reglas!$C$7,ABS(N(AB12))>Reglas!$C$8),"Conciliado (revisar)",IF(OR(N12="Varios CFDI",N12="Parcial"),"Conciliado (validar)","Conciliado"))) | AK12: =IF(AL12=1,ROUND(SUMIF($A$8:$A$114,A12,$D$8:$D$114)+SUMIF($A$8:$A$114,A12,$E$8:$E$114)-SUMIF($A$8:$A$114,A12,$W$8:$W$114),2),0)
L13: =IF(OR(F13="",AL13=0),"",(D13+E13)-(J13+K13)) | M13: =IF(OR(F13="",AL13=0,B13=""),"",G13-B13) | X13: =IF(OR(V13="",V13=0),0,ROUND(W13/V13*AF13,2)) | Y13: =IF(OR(V13="",V13=0),0,ROUND(W13/V13*AG13,2)) | Z13: =IF(OR(V13="",V13=0),0,ROUND(W13/V13*AH13,2)) | AA13: =IF(OR(V13="",V13=0),0,ROUND(W13/V13*AI13,2)) | AC13: =ROUND(SUMIF($A$8:$A$114,A13,$D$8:$D$114)+SUMIF($A$8:$A$114,A13,$E$8:$E$114)-SUMIF($A$8:$A$114,A13,$W$8:$W$114),2) | AD13: =IF(OR((SUMIF($A$8:$A$114,A13,$D$8:$D$114)+SUMIF($A$8:$A$114,A13,$E$8:$E$114))=0,COUNTIFS($A$8:$A$114,A13,$F$8:$F$114,"?*")=0,N13="Sin CFDI"),"No identificado",IF(OR(ABS(SUMIF($A$8:$A$114,A13,$L$8:$L$114))>Reglas!$C$7,ABS(SUMIF($A$8:$A$114,A13,$M$8:$M$114))>Reglas!$C$8,ABS(AC13)>Reglas!$C$7,ABS(N(AB13))>Reglas!$C$8),"Conciliado (revisar)",IF(OR(N13="Varios CFDI",N13="Parcial"),"Conciliado (validar)","Conciliado"))) | AK13: =IF(AL13=1,ROUND(SUMIF($A$8:$A$114,A13,$D$8:$D$114)+SUMIF($A$8:$A$114,A13,$E$8:$E$114)-SUMIF($A$8:$A$114,A13,$W$8:$W$114),2),0)
L14: =IF(OR(F14="",AL14=0),"",(D14+E14)-(J14+K14)) | M14: =IF(OR(F14="",AL14=0,B14=""),"",G14-B14) | X14: =IF(OR(V14="",V14=0),0,ROUND(W14/V14*AF14,2)) | Y14: =IF(OR(V14="",V14=0),0,ROUND(W14/V14*AG14,2)) | Z14: =IF(OR(V14="",V14=0),0,ROUND(W14/V14*AH14,2)) | AA14: =IF(OR(V14="",V14=0),0,ROUND(W14/V14*AI14,2)) | AC14: =ROUND(SUMIF($A$8:$A$114,A14,$D$8:$D$114)+SUMIF($A$8:$A$114,A14,$E$8:$E$114)-SUMIF($A$8:$A$114,A14,$W$8:$W$114),2) | AD14: =IF(OR((SUMIF($A$8:$A$114,A14,$D$8:$D$114)+SUMIF($A$8:$A$114,A14,$E$8:$E$114))=0,COUNTIFS($A$8:$A$114,A14,$F$8:$F$114,"?*")=0,N14="Sin CFDI"),"No identificado",IF(OR(ABS(SUMIF($A$8:$A$114,A14,$L$8:$L$114))>Reglas!$C$7,ABS(SUMIF($A$8:$A$114,A14,$M$8:$M$114))>Reglas!$C$8,ABS(AC14)>Reglas!$C$7,ABS(N(AB14))>Reglas!$C$8),"Conciliado (revisar)",IF(OR(N14="Varios CFDI",N14="Parcial"),"Conciliado (validar)","Conciliado"))) | AK14: =IF(AL14=1,ROUND(SUMIF($A$8:$A$114,A14,$D$8:$D$114)+SUMIF($A$8:$A$114,A14,$E$8:$E$114)-SUMIF($A$8:$A$114,A14,$W$8:$W$114),2),0)
L15: =IF(OR(F15="",AL15=0),"",(D15+E15)-(J15+K15)) | M15: =IF(OR(F15="",AL15=0,B15=""),"",G15-B15) | X15: =IF(OR(V15="",V15=0),0,ROUND(W15/V15*AF15,2)) | Y15: =IF(OR(V15="",V15=0),0,ROUND(W15/V15*AG15,2)) | Z15: =IF(OR(V15="",V15=0),0,ROUND(W15/V15*AH15,2)) | AA15: =IF(OR(V15="",V15=0),0,ROUND(W15/V15*AI15,2)) | AC15: =ROUND(SUMIF($A$8:$A$114,A15,$D$8:$D$114)+SUMIF($A$8:$A$114,A15,$E$8:$E$114)-SUMIF($A$8:$A$114,A15,$W$8:$W$114),2) | AD15: =IF(OR((SUMIF($A$8:$A$114,A15,$D$8:$D$114)+SUMIF($A$8:$A$114,A15,$E$8:$E$114))=0,COUNTIFS($A$8:$A$114,A15,$F$8:$F$114,"?*")=0,N15="Sin CFDI"),"No identificado",IF(OR(ABS(SUMIF($A$8:$A$114,A15,$L$8:$L$114))>Reglas!$C$7,ABS(SUMIF($A$8:$A$114,A15,$M$8:$M$114))>Reglas!$C$8,ABS(AC15)>Reglas!$C$7,ABS(N(AB15))>Reglas!$C$8),"Conciliado (revisar)",IF(OR(N15="Varios CFDI",N15="Parcial"),"Conciliado (validar)","Conciliado"))) | AK15: =IF(AL15=1,ROUND(SUMIF($A$8:$A$114,A15,$D$8:$D$114)+SUMIF($A$8:$A$114,A15,$E$8:$E$114)-SUMIF($A$8:$A$114,A15,$W$8:$W$114),2),0)
L16: =IF(OR(F16="",AL16=0),"",(D16+E16)-(J16+K16)) | M16: =IF(OR(F16="",AL16=0,B16=""),"",G16-B16) | X16: =IF(OR(V16="",V16=0),0,ROUND(W16/V16*AF16,2)) | Y16: =IF(OR(V16="",V16=0),0,ROUND(W16/V16*AG16,2)) | Z16: =IF(OR(V16="",V16=0),0,ROUND(W16/V16*AH16,2)) | AA16: =IF(OR(V16="",V16=0),0,ROUND(W16/V16*AI16,2)) | AC16: =ROUND(SUMIF($A$8:$A$114,A16,$D$8:$D$114)+SUMIF($A$8:$A$114,A16,$E$8:$E$114)-SUMIF($A$8:$A$114,A16,$W$8:$W$114),2) | AD16: =IF(OR((SUMIF($A$8:$A$114,A16,$D$8:$D$114)+SUMIF($A$8:$A$114,A16,$E$8:$E$114))=0,COUNTIFS($A$8:$A$114,A16,$F$8:$F$114,"?*")=0,N16="Sin CFDI"),"No identificado",IF(OR(ABS(SUMIF($A$8:$A$114,A16,$L$8:$L$114))>Reglas!$C$7,ABS(SUMIF($A$8:$A$114,A16,$M$8:$M$114))>Reglas!$C$8,ABS(AC16)>Reglas!$C$7,ABS(N(AB16))>Reglas!$C$8),"Conciliado (revisar)",IF(OR(N16="Varios CFDI",N16="Parcial"),"Conciliado (validar)","Conciliado"))) | AK16: =IF(AL16=1,ROUND(SUMIF($A$8:$A$114,A16,$D$8:$D$114)+SUMIF($A$8:$A$114,A16,$E$8:$E$114)-SUMIF($A$8:$A$114,A16,$W$8:$W$114),2),0)
L17: =IF(OR(F17="",AL17=0),"",(D17+E17)-(J17+K17)) | M17: =IF(OR(F17="",AL17=0,B17=""),"",G17-B17) | X17: =IF(OR(V17="",V17=0),0,ROUND(W17/V17*AF17,2)) | Y17: =IF(OR(V17="",V17=0),0,ROUND(W17/V17*AG17,2)) | Z17: =IF(OR(V17="",V17=0),0,ROUND(W17/V17*AH17,2)) | AA17: =IF(OR(V17="",V17=0),0,ROUND(W17/V17*AI17,2)) | AC17: =ROUND(SUMIF($A$8:$A$114,A17,$D$8:$D$114)+SUMIF($A$8:$A$114,A17,$E$8:$E$114)-SUMIF($A$8:$A$114,A17,$W$8:$W$114),2) | AD17: =IF(OR((SUMIF($A$8:$A$114,A17,$D$8:$D$114)+SUMIF($A$8:$A$114,A17,$E$8:$E$114))=0,COUNTIFS($A$8:$A$114,A17,$F$8:$F$114,"?*")=0,N17="Sin CFDI"),"No identificado",IF(OR(ABS(SUMIF($A$8:$A$114,A17,$L$8:$L$114))>Reglas!$C$7,ABS(SUMIF($A$8:$A$114,A17,$M$8:$M$114))>Reglas!$C$8,ABS(AC17)>Reglas!$C$7,ABS(N(AB17))>Reglas!$C$8),"Conciliado (revisar)",IF(OR(N17="Varios CFDI",N17="Parcial"),"Conciliado (validar)","Conciliado"))) | AK17: =IF(AL17=1,ROUND(SUMIF($A$8:$A$114,A17,$D$8:$D$114)+SUMIF($A$8:$A$114,A17,$E$8:$E$114)-SUMIF($A$8:$A$114,A17,$W$8:$W$114),2),0)
L18: =IF(OR(F18="",AL18=0),"",(D18+E18)-(J18+K18)) | M18: =IF(OR(F18="",AL18=0,B18=""),"",G18-B18) | X18: =IF(OR(V18="",V18=0),0,ROUND(W18/V18*AF18,2)) | Y18: =IF(OR(V18="",V18=0),0,ROUND(W18/V18*AG18,2)) | Z18: =IF(OR(V18="",V18=0),0,ROUND(W18/V18*AH18,2)) | AA18: =IF(OR(V18="",V18=0),0,ROUND(W18/V18*AI18,2)) | AC18: =ROUND(SUMIF($A$8:$A$114,A18,$D$8:$D$114)+SUMIF($A$8:$A$114,A18,$E$8:$E$114)-SUMIF($A$8:$A$114,A18,$W$8:$W$114),2) | AD18: =IF(OR((SUMIF($A$8:$A$114,A18,$D$8:$D$114)+SUMIF($A$8:$A$114,A18,$E$8:$E$114))=0,COUNTIFS($A$8:$A$114,A18,$F$8:$F$114,"?*")=0,N18="Sin CFDI"),"No identificado",IF(OR(ABS(SUMIF($A$8:$A$114,A18,$L$8:$L$114))>Reglas!$C$7,ABS(SUMIF($A$8:$A$114,A18,$M$8:$M$114))>Reglas!$C$8,ABS(AC18)>Reglas!$C$7,ABS(N(AB18))>Reglas!$C$8),"Conciliado (revisar)",IF(OR(N18="Varios CFDI",N18="Parcial"),"Conciliado (validar)","Conciliado"))) | AK18: =IF(AL18=1,ROUND(SUMIF($A$8:$A$114,A18,$D$8:$D$114)+SUMIF($A$8:$A$114,A18,$E$8:$E$114)-SUMIF($A$8:$A$114,A18,$W$8:$W$114),2),0)
L19: =IF(OR(F19="",AL19=0),"",(D19+E19)-(J19+K19)) | M19: =IF(OR(F19="",AL19=0,B19=""),"",G19-B19) | X19: =IF(OR(V19="",V19=0),0,ROUND(W19/V19*AF19,2)) | Y19: =IF(OR(V19="",V19=0),0,ROUND(W19/V19*AG19,2)) | Z19: =IF(OR(V19="",V19=0),0,ROUND(W19/V19*AH19,2)) | AA19: =IF(OR(V19="",V19=0),0,ROUND(W19/V19*AI19,2)) | AC19: =ROUND(SUMIF($A$8:$A$114,A19,$D$8:$D$114)+SUMIF($A$8:$A$114,A19,$E$8:$E$114)-SUMIF($A$8:$A$114,A19,$W$8:$W$114),2) | AD19: =IF(OR((SUMIF($A$8:$A$114,A19,$D$8:$D$114)+SUMIF($A$8:$A$114,A19,$E$8:$E$114))=0,COUNTIFS($A$8:$A$114,A19,$F$8:$F$114,"?*")=0,N19="Sin CFDI"),"No identificado",IF(OR(ABS(SUMIF($A$8:$A$114,A19,$L$8:$L$114))>Reglas!$C$7,ABS(SUMIF($A$8:$A$114,A19,$M$8:$M$114))>Reglas!$C$8,ABS(AC19)>Reglas!$C$7,ABS(N(AB19))>Reglas!$C$8),"Conciliado (revisar)",IF(OR(N19="Varios CFDI",N19="Parcial"),"Conciliado (validar)","Conciliado"))) | AK19: =IF(AL19=1,ROUND(SUMIF($A$8:$A$114,A19,$D$8:$D$114)+SUMIF($A$8:$A$114,A19,$E$8:$E$114)-SUMIF($A$8:$A$114,A19,$W$8:$W$114),2),0)
... L114: =IF(OR(F114="",AL114=0),"",(D114+E114)-(J114+K114)) | M114: =IF(OR(F114="",AL114=0,B114=""),"",G114-B114) | X114: =IF(OR(V114="",V114=0),0,ROUND(W114/V114*AF114,2)) | Y114: =IF(OR(V114="",V114=0),0,ROUND(W114/V114*AG114,2)) | Z114: =IF(OR(V114="",V114=0),0,ROUND(W114/V114*AH114,2)) | AA114: =IF(OR(V114="",V114=0),0,ROUND(W114/V114*AI114,2)) | AC114: =ROUND(SUMIF($A$8:$A$114,A114,$D$8:$D$114)+SUMIF($A$8:$A$114,A114,$E$8:$E$114)-SUMIF($A$8:$A$114,A114,$W$8:$W$114),2) | AD114: =IF(OR((SUMIF($A$8:$A$114,A114,$D$8:$D$114)+SUMIF($A$8:$A$114,A114,$E$8:$E$114))=0,COUNTIFS($A$8:$A$114,A114,$F$8:$F$114,"?*")=0,N114="Sin CFDI"),"No identificado",IF(OR(ABS(SUMIF($A$8:$A$114,A114,$L$8:$L$114))>Reglas!$C$7,ABS(SUMIF($A$8:$A$114,A114,$M$8:$M$114))>Reglas!$C$8,ABS(AC114)>Reglas!$C$7,ABS(N(AB114))>Reglas!$C$8),"Conciliado (revisar)",IF(OR(N114="Varios CFDI",N114="Parcial"),"Conciliado (validar)","Conciliado"))) | AK114: =IF(AL114=1,ROUND(SUMIF($A$8:$A$114,A114,$D$8:$D$114)+SUMIF($A$8:$A$114,A114,$E$8:$E$114)-SUMIF($A$8:$A$114,A114,$W$8:$W$114),2),0)
C115: Totales | D115: =SUM(D8:D114) | E115: =SUM(E8:E114) | J115: =SUM(J8:J114) | K115: =SUM(K8:K114) | W115: =SUM(W8:W114) | X115: =SUM(X8:X114) | Y115: =SUM(Y8:Y114) | Z115: =SUM(Z8:Z114) | AA115: =SUM(AA8:AA114)

Sheet Facturas vs Odoo
C1: MLR CONSULTORES
C2: Facturas del mes: SAT contra Odoo
C3: <Empresa> · <Mes Año>
A5: Cada CFDI del mes emitido o recibido se busca en Odoo: las emitidas por serie y folio, las recibidas por folio fiscal. Revisa estado e importe.
A7: Tipo | B7: Número en Odoo | C7: UUID | D7: Fecha CFDI | E7: Cliente o proveedor | F7: Estado SAT | G7: Total CFDI | H7: Estado en Odoo | I7: Total Odoo | J7: Pendiente en Odoo | K7: Diferencia | L7: Estatus | M7: Observación
K8: =IF(OR(G8="",I8=""),"",ROUND(G8-I8,2)) | L8: =IF(OR(B8="",G8=""),"No identificado",IF(AND(F8="Cancelado",H8="Cancelado"),"Conciliado",IF(OR(F8="Cancelado",H8="Cancelado"),"Conciliado (revisar)",IF(ABS(K8)>Reglas!$C$7,"Conciliado (revisar)","Conciliado"))))
K9: =IF(OR(G9="",I9=""),"",ROUND(G9-I9,2)) | L9: =IF(OR(B9="",G9=""),"No identificado",IF(AND(F9="Cancelado",H9="Cancelado"),"Conciliado",IF(OR(F9="Cancelado",H9="Cancelado"),"Conciliado (revisar)",IF(ABS(K9)>Reglas!$C$7,"Conciliado (revisar)","Conciliado"))))
K10: =IF(OR(G10="",I10=""),"",ROUND(G10-I10,2)) | L10: =IF(OR(B10="",G10=""),"No identificado",IF(AND(F10="Cancelado",H10="Cancelado"),"Conciliado",IF(OR(F10="Cancelado",H10="Cancelado"),"Conciliado (revisar)",IF(ABS(K10)>Reglas!$C$7,"Conciliado (revisar)","Conciliado"))))
K11: =IF(OR(G11="",I11=""),"",ROUND(G11-I11,2)) | L11: =IF(OR(B11="",G11=""),"No identificado",IF(AND(F11="Cancelado",H11="Cancelado"),"Conciliado",IF(OR(F11="Cancelado",H11="Cancelado"),"Conciliado (revisar)",IF(ABS(K11)>Reglas!$C$7,"Conciliado (revisar)","Conciliado"))))
K12: =IF(OR(G12="",I12=""),"",ROUND(G12-I12,2)) | L12: =IF(OR(B12="",G12=""),"No identificado",IF(AND(F12="Cancelado",H12="Cancelado"),"Conciliado",IF(OR(F12="Cancelado",H12="Cancelado"),"Conciliado (revisar)",IF(ABS(K12)>Reglas!$C$7,"Conciliado (revisar)","Conciliado"))))
K13: =IF(OR(G13="",I13=""),"",ROUND(G13-I13,2)) | L13: =IF(OR(B13="",G13=""),"No identificado",IF(AND(F13="Cancelado",H13="Cancelado"),"Conciliado",IF(OR(F13="Cancelado",H13="Cancelado"),"Conciliado (revisar)",IF(ABS(K13)>Reglas!$C$7,"Conciliado (revisar)","Conciliado"))))
K14: =IF(OR(G14="",I14=""),"",ROUND(G14-I14,2)) | L14: =IF(OR(B14="",G14=""),"No identificado",IF(AND(F14="Cancelado",H14="Cancelado"),"Conciliado",IF(OR(F14="Cancelado",H14="Cancelado"),"Conciliado (revisar)",IF(ABS(K14)>Reglas!$C$7,"Conciliado (revisar)","Conciliado"))))
K15: =IF(OR(G15="",I15=""),"",ROUND(G15-I15,2)) | L15: =IF(OR(B15="",G15=""),"No identificado",IF(AND(F15="Cancelado",H15="Cancelado"),"Conciliado",IF(OR(F15="Cancelado",H15="Cancelado"),"Conciliado (revisar)",IF(ABS(K15)>Reglas!$C$7,"Conciliado (revisar)","Conciliado"))))
K16: =IF(OR(G16="",I16=""),"",ROUND(G16-I16,2)) | L16: =IF(OR(B16="",G16=""),"No identificado",IF(AND(F16="Cancelado",H16="Cancelado"),"Conciliado",IF(OR(F16="Cancelado",H16="Cancelado"),"Conciliado (revisar)",IF(ABS(K16)>Reglas!$C$7,"Conciliado (revisar)","Conciliado"))))
K17: =IF(OR(G17="",I17=""),"",ROUND(G17-I17,2)) | L17: =IF(OR(B17="",G17=""),"No identificado",IF(AND(F17="Cancelado",H17="Cancelado"),"Conciliado",IF(OR(F17="Cancelado",H17="Cancelado"),"Conciliado (revisar)",IF(ABS(K17)>Reglas!$C$7,"Conciliado (revisar)","Conciliado"))))
K18: =IF(OR(G18="",I18=""),"",ROUND(G18-I18,2)) | L18: =IF(OR(B18="",G18=""),"No identificado",IF(AND(F18="Cancelado",H18="Cancelado"),"Conciliado",IF(OR(F18="Cancelado",H18="Cancelado"),"Conciliado (revisar)",IF(ABS(K18)>Reglas!$C$7,"Conciliado (revisar)","Conciliado"))))
K19: =IF(OR(G19="",I19=""),"",ROUND(G19-I19,2)) | L19: =IF(OR(B19="",G19=""),"No identificado",IF(AND(F19="Cancelado",H19="Cancelado"),"Conciliado",IF(OR(F19="Cancelado",H19="Cancelado"),"Conciliado (revisar)",IF(ABS(K19)>Reglas!$C$7,"Conciliado (revisar)","Conciliado"))))
... K94: =IF(OR(G94="",I94=""),"",ROUND(G94-I94,2)) | L94: =IF(OR(B94="",G94=""),"No identificado",IF(AND(F94="Cancelado",H94="Cancelado"),"Conciliado",IF(OR(F94="Cancelado",H94="Cancelado"),"Conciliado (revisar)",IF(ABS(K94)>Reglas!$C$7,"Conciliado (revisar)","Conciliado"))))

Sheet Impuestos vs Odoo
C1: MLR CONSULTORES
C2: IVA del mes: Odoo contra la conciliación
C3: <Empresa> · <Mes Año>
A5: Compara, factura por factura, el IVA que Odoo registró en sus cuentas de flujo (208.01 y 118.01) contra el IVA que resulta de los cobros y pagos conciliados.
A7: Saldos de las cuentas de IVA en Odoo
A8: Cuenta | B8: Nombre | C8: Saldo inicial | D8: Movimiento del mes | E8: Saldo final | F8: Según la conciliación | G8: Diferencia
A9: 118.01.01 | B9: IVA acreditable pagado | D9: =E9-C9 | F9: ='Desglose fiscal'!C32 | G9: =ROUND(D9-F9,2)
A10: 208.01.01 | B10: IVA trasladado cobrado | D10: =E10-C10 | F10: ='Desglose fiscal'!C18 | G10: =ROUND(D10-F10,2)
A12: Signos: el IVA trasladado se muestra en positivo para leerlo igual que el acreditable. Fuente: libro mayor del mes leído de Odoo.
A14: Detalle por factura
A15: IVA | B15: Cuenta | C15: Factura en Odoo | D15: Contacto | E15: UUID | F15: IVA en Odoo | G15: IVA en la conciliación | H15: Diferencia | I15: Estatus | J15: Observación | K15: Diario
G16: =IF(E16="","",SUMIFS(Conciliación!$Y$8:$Y$114,Conciliación!$O$8:$O$114,E16,Conciliación!$AJ$8:$AJ$114,IF(A16="Trasladado","Cobro","Pago"))) | H16: =IF(G16="","",ROUND(F16-G16,2)) | I16: =IF(ISNUMBER(SEARCH("CSH1",K16)),"Conciliado (validar)",IF(E16="","Conciliado (revisar)",IF(AND(ABS(F16)<0.01,ABS(G16)<0.01),"Conciliado",IF(G16=0,"No identificado",IF(ABS(H16)>Reglas!$C$7,"Conciliado (revisar)","Conciliado")))))
G17: =IF(E17="","",SUMIFS(Conciliación!$Y$8:$Y$114,Conciliación!$O$8:$O$114,E17,Conciliación!$AJ$8:$AJ$114,IF(A17="Trasladado","Cobro","Pago"))) | H17: =IF(G17="","",ROUND(F17-G17,2)) | I17: =IF(ISNUMBER(SEARCH("CSH1",K17)),"Conciliado (validar)",IF(E17="","Conciliado (revisar)",IF(AND(ABS(F17)<0.01,ABS(G17)<0.01),"Conciliado",IF(G17=0,"No identificado",IF(ABS(H17)>Reglas!$C$7,"Conciliado (revisar)","Conciliado")))))
G18: =IF(E18="","",SUMIFS(Conciliación!$Y$8:$Y$114,Conciliación!$O$8:$O$114,E18,Conciliación!$AJ$8:$AJ$114,IF(A18="Trasladado","Cobro","Pago"))) | H18: =IF(G18="","",ROUND(F18-G18,2)) | I18: =IF(ISNUMBER(SEARCH("CSH1",K18)),"Conciliado (validar)",IF(E18="","Conciliado (revisar)",IF(AND(ABS(F18)<0.01,ABS(G18)<0.01),"Conciliado",IF(G18=0,"No identificado",IF(ABS(H18)>Reglas!$C$7,"Conciliado (revisar)","Conciliado")))))
G19: =IF(E19="","",SUMIFS(Conciliación!$Y$8:$Y$114,Conciliación!$O$8:$O$114,E19,Conciliación!$AJ$8:$AJ$114,IF(A19="Trasladado","Cobro","Pago"))) | H19: =IF(G19="","",ROUND(F19-G19,2)) | I19: =IF(ISNUMBER(SEARCH("CSH1",K19)),"Conciliado (validar)",IF(E19="","Conciliado (revisar)",IF(AND(ABS(F19)<0.01,ABS(G19)<0.01),"Conciliado",IF(G19=0,"No identificado",IF(ABS(H19)>Reglas!$C$7,"Conciliado (revisar)","Conciliado")))))
G20: =IF(E20="","",SUMIFS(Conciliación!$Y$8:$Y$114,Conciliación!$O$8:$O$114,E20,Conciliación!$AJ$8:$AJ$114,IF(A20="Trasladado","Cobro","Pago"))) | H20: =IF(G20="","",ROUND(F20-G20,2)) | I20: =IF(ISNUMBER(SEARCH("CSH1",K20)),"Conciliado (validar)",IF(E20="","Conciliado (revisar)",IF(AND(ABS(F20)<0.01,ABS(G20)<0.01),"Conciliado",IF(G20=0,"No identificado",IF(ABS(H20)>Reglas!$C$7,"Conciliado (revisar)","Conciliado")))))
G21: =IF(E21="","",SUMIFS(Conciliación!$Y$8:$Y$114,Conciliación!$O$8:$O$114,E21,Conciliación!$AJ$8:$AJ$114,IF(A21="Trasladado","Cobro","Pago"))) | H21: =IF(G21="","",ROUND(F21-G21,2)) | I21: =IF(ISNUMBER(SEARCH("CSH1",K21)),"Conciliado (validar)",IF(E21="","Conciliado (revisar)",IF(AND(ABS(F21)<0.01,ABS(G21)<0.01),"Conciliado",IF(G21=0,"No identificado",IF(ABS(H21)>Reglas!$C$7,"Conciliado (revisar)","Conciliado")))))
G22: =IF(E22="","",SUMIFS(Conciliación!$Y$8:$Y$114,Conciliación!$O$8:$O$114,E22,Conciliación!$AJ$8:$AJ$114,IF(A22="Trasladado","Cobro","Pago"))) | H22: =IF(G22="","",ROUND(F22-G22,2)) | I22: =IF(ISNUMBER(SEARCH("CSH1",K22)),"Conciliado (validar)",IF(E22="","Conciliado (revisar)",IF(AND(ABS(F22)<0.01,ABS(G22)<0.01),"Conciliado",IF(G22=0,"No identificado",IF(ABS(H22)>Reglas!$C$7,"Conciliado (revisar)","Conciliado")))))
G23: =IF(E23="","",SUMIFS(Conciliación!$Y$8:$Y$114,Conciliación!$O$8:$O$114,E23,Conciliación!$AJ$8:$AJ$114,IF(A23="Trasladado","Cobro","Pago"))) | H23: =IF(G23="","",ROUND(F23-G23,2)) | I23: =IF(ISNUMBER(SEARCH("CSH1",K23)),"Conciliado (validar)",IF(E23="","Conciliado (revisar)",IF(AND(ABS(F23)<0.01,ABS(G23)<0.01),"Conciliado",IF(G23=0,"No identificado",IF(ABS(H23)>Reglas!$C$7,"Conciliado (revisar)","Conciliado")))))
G24: =IF(E24="","",SUMIFS(Conciliación!$Y$8:$Y$114,Conciliación!$O$8:$O$114,E24,Conciliación!$AJ$8:$AJ$114,IF(A24="Trasladado","Cobro","Pago"))) | H24: =IF(G24="","",ROUND(F24-G24,2)) | I24: =IF(ISNUMBER(SEARCH("CSH1",K24)),"Conciliado (validar)",IF(E24="","Conciliado (revisar)",IF(AND(ABS(F24)<0.01,ABS(G24)<0.01),"Conciliado",IF(G24=0,"No identificado",IF(ABS(H24)>Reglas!$C$7,"Conciliado (revisar)","Conciliado")))))
G25: =IF(E25="","",SUMIFS(Conciliación!$Y$8:$Y$114,Conciliación!$O$8:$O$114,E25,Conciliación!$AJ$8:$AJ$114,IF(A25="Trasladado","Cobro","Pago"))) | H25: =IF(G25="","",ROUND(F25-G25,2)) | I25: =IF(ISNUMBER(SEARCH("CSH1",K25)),"Conciliado (validar)",IF(E25="","Conciliado (revisar)",IF(AND(ABS(F25)<0.01,ABS(G25)<0.01),"Conciliado",IF(G25=0,"No identificado",IF(ABS(H25)>Reglas!$C$7,"Conciliado (revisar)","Conciliado")))))
G26: =IF(E26="","",SUMIFS(Conciliación!$Y$8:$Y$114,Conciliación!$O$8:$O$114,E26,Conciliación!$AJ$8:$AJ$114,IF(A26="Trasladado","Cobro","Pago"))) | H26: =IF(G26="","",ROUND(F26-G26,2)) | I26: =IF(ISNUMBER(SEARCH("CSH1",K26)),"Conciliado (validar)",IF(E26="","Conciliado (revisar)",IF(AND(ABS(F26)<0.01,ABS(G26)<0.01),"Conciliado",IF(G26=0,"No identificado",IF(ABS(H26)>Reglas!$C$7,"Conciliado (revisar)","Conciliado")))))
G27: =IF(E27="","",SUMIFS(Conciliación!$Y$8:$Y$114,Conciliación!$O$8:$O$114,E27,Conciliación!$AJ$8:$AJ$114,IF(A27="Trasladado","Cobro","Pago"))) | H27: =IF(G27="","",ROUND(F27-G27,2)) | I27: =IF(ISNUMBER(SEARCH("CSH1",K27)),"Conciliado (validar)",IF(E27="","Conciliado (revisar)",IF(AND(ABS(F27)<0.01,ABS(G27)<0.01),"Conciliado",IF(G27=0,"No identificado",IF(ABS(H27)>Reglas!$C$7,"Conciliado (revisar)","Conciliado")))))
... G95: =IF(E95="","",SUMIFS(Conciliación!$Y$8:$Y$114,Conciliación!$O$8:$O$114,E95,Conciliación!$AJ$8:$AJ$114,IF(A95="Trasladado","Cobro","Pago"))) | H95: =IF(G95="","",ROUND(F95-G95,2)) | I95: =IF(ISNUMBER(SEARCH("CSH1",K95)),"Conciliado (validar)",IF(E95="","Conciliado (revisar)",IF(AND(ABS(F95)<0.01,ABS(G95)<0.01),"Conciliado",IF(G95=0,"No identificado",IF(ABS(H95)>Reglas!$C$7,"Conciliado (revisar)","Conciliado")))))
F99: =SUMIFS('Impuestos vs Odoo'!$F$16:$F$95,'Impuestos vs Odoo'!$A$16:$A$95,"Trasladado",'Impuestos vs Odoo'!$I$16:$I$95,"No identificado")
F100: =SUMIFS('Impuestos vs Odoo'!$H$16:$H$95,'Impuestos vs Odoo'!$A$16:$A$95,"Trasladado",'Impuestos vs Odoo'!$I$16:$I$95,"Conciliado (revisar)")
F101: =SUMIFS('Impuestos vs Odoo'!$F$16:$F$95,'Impuestos vs Odoo'!$A$16:$A$95,"Acreditable",'Impuestos vs Odoo'!$K$16:$K$95,"*CSH1*",'Impuestos vs Odoo'!$G$16:$G$95,0)
F102: =SUMIFS('Impuestos vs Odoo'!$F$16:$F$95,'Impuestos vs Odoo'!$A$16:$A$95,"Acreditable",'Impuestos vs Odoo'!$I$16:$I$95,"No identificado")
F103: =SUMIFS('Impuestos vs Odoo'!$F$16:$F$95,'Impuestos vs Odoo'!$A$16:$A$95,"Acreditable",'Impuestos vs Odoo'!$E$16:$E$95,"")
F104: =ROUND('Desglose fiscal'!B40/1.16*0.16,2)

Sheet Desglose fiscal
C1: MLR CONSULTORES
C2: Impuestos del mes por flujo de efectivo
C3: <Empresa> · <Mes Año>
A5: Solo lo cobrado y lo pagado en el mes según el banco, separado por tipo de retención. Sale de la hoja Conciliación y se actualiza solo.
A7: Cobros a clientes: IVA trasladado cobrado
A8: Tipo de retención | B8: Base | C8: IVA | D8: IVA retenido | E8: ISR retenido | F8: Renglones
A9: Sin retención | B9: =SUMIFS(Conciliación!$X$8:$X$114,Conciliación!$AJ$8:$AJ$114,"Cobro",Conciliación!$U$8:$U$114,$A9) | C9: =SUMIFS(Conciliación!$Y$8:$Y$114,Conciliación!$AJ$8:$AJ$114,"Cobro",Conciliación!$U$8:$U$114,$A9) | D9: =SUMIFS(Conciliación!$Z$8:$Z$114,Conciliación!$AJ$8:$AJ$114,"Cobro",Conciliación!$U$8:$U$114,$A9) | E9: =SUMIFS(Conciliación!$AA$8:$AA$114,Conciliación!$AJ$8:$AJ$114,"Cobro",Conciliación!$U$8:$U$114,$A9) | F9: =COUNTIFS(Conciliación!$AJ$8:$AJ$114,"Cobro",Conciliación!$U$8:$U$114,$A9)
A10: Honorarios | B10: =SUMIFS(Conciliación!$X$8:$X$114,Conciliación!$AJ$8:$AJ$114,"Cobro",Conciliación!$U$8:$U$114,$A10) | C10: =SUMIFS(Conciliación!$Y$8:$Y$114,Conciliación!$AJ$8:$AJ$114,"Cobro",Conciliación!$U$8:$U$114,$A10) | D10: =SUMIFS(Conciliación!$Z$8:$Z$114,Conciliación!$AJ$8:$AJ$114,"Cobro",Conciliación!$U$8:$U$114,$A10) | E10: =SUMIFS(Conciliación!$AA$8:$AA$114,Conciliación!$AJ$8:$AJ$114,"Cobro",Conciliación!$U$8:$U$114,$A10) | F10: =COUNTIFS(Conciliación!$AJ$8:$AJ$114,"Cobro",Conciliación!$U$8:$U$114,$A10)
A11: Arrendamiento | B11: =SUMIFS(Conciliación!$X$8:$X$114,Conciliación!$AJ$8:$AJ$114,"Cobro",Conciliación!$U$8:$U$114,$A11) | C11: =SUMIFS(Conciliación!$Y$8:$Y$114,Conciliación!$AJ$8:$AJ$114,"Cobro",Conciliación!$U$8:$U$114,$A11) | D11: =SUMIFS(Conciliación!$Z$8:$Z$114,Conciliación!$AJ$8:$AJ$114,"Cobro",Conciliación!$U$8:$U$114,$A11) | E11: =SUMIFS(Conciliación!$AA$8:$AA$114,Conciliación!$AJ$8:$AJ$114,"Cobro",Conciliación!$U$8:$U$114,$A11) | F11: =COUNTIFS(Conciliación!$AJ$8:$AJ$114,"Cobro",Conciliación!$U$8:$U$114,$A11)
A12: RESICO actividad empresarial | B12: =SUMIFS(Conciliación!$X$8:$X$114,Conciliación!$AJ$8:$AJ$114,"Cobro",Conciliación!$U$8:$U$114,$A12) | C12: =SUMIFS(Conciliación!$Y$8:$Y$114,Conciliación!$AJ$8:$AJ$114,"Cobro",Conciliación!$U$8:$U$114,$A12) | D12: =SUMIFS(Conciliación!$Z$8:$Z$114,Conciliación!$AJ$8:$AJ$114,"Cobro",Conciliación!$U$8:$U$114,$A12) | E12: =SUMIFS(Conciliación!$AA$8:$AA$114,Conciliación!$AJ$8:$AJ$114,"Cobro",Conciliación!$U$8:$U$114,$A12) | F12: =COUNTIFS(Conciliación!$AJ$8:$AJ$114,"Cobro",Conciliación!$U$8:$U$114,$A12)
A13: RESICO honorarios | B13: =SUMIFS(Conciliación!$X$8:$X$114,Conciliación!$AJ$8:$AJ$114,"Cobro",Conciliación!$U$8:$U$114,$A13) | C13: =SUMIFS(Conciliación!$Y$8:$Y$114,Conciliación!$AJ$8:$AJ$114,"Cobro",Conciliación!$U$8:$U$114,$A13) | D13: =SUMIFS(Conciliación!$Z$8:$Z$114,Conciliación!$AJ$8:$AJ$114,"Cobro",Conciliación!$U$8:$U$114,$A13) | E13: =SUMIFS(Conciliación!$AA$8:$AA$114,Conciliación!$AJ$8:$AJ$114,"Cobro",Conciliación!$U$8:$U$114,$A13) | F13: =COUNTIFS(Conciliación!$AJ$8:$AJ$114,"Cobro",Conciliación!$U$8:$U$114,$A13)
A14: RESICO arrendamiento | B14: =SUMIFS(Conciliación!$X$8:$X$114,Conciliación!$AJ$8:$AJ$114,"Cobro",Conciliación!$U$8:$U$114,$A14) | C14: =SUMIFS(Conciliación!$Y$8:$Y$114,Conciliación!$AJ$8:$AJ$114,"Cobro",Conciliación!$U$8:$U$114,$A14) | D14: =SUMIFS(Conciliación!$Z$8:$Z$114,Conciliación!$AJ$8:$AJ$114,"Cobro",Conciliación!$U$8:$U$114,$A14) | E14: =SUMIFS(Conciliación!$AA$8:$AA$114,Conciliación!$AJ$8:$AJ$114,"Cobro",Conciliación!$U$8:$U$114,$A14) | F14: =COUNTIFS(Conciliación!$AJ$8:$AJ$114,"Cobro",Conciliación!$U$8:$U$114,$A14)
A15: Fletes | B15: =SUMIFS(Conciliación!$X$8:$X$114,Conciliación!$AJ$8:$AJ$114,"Cobro",Conciliación!$U$8:$U$114,$A15) | C15: =SUMIFS(Conciliación!$Y$8:$Y$114,Conciliación!$AJ$8:$AJ$114,"Cobro",Conciliación!$U$8:$U$114,$A15) | D15: =SUMIFS(Conciliación!$Z$8:$Z$114,Conciliación!$AJ$8:$AJ$114,"Cobro",Conciliación!$U$8:$U$114,$A15) | E15: =SUMIFS(Conciliación!$AA$8:$AA$114,Conciliación!$AJ$8:$AJ$114,"Cobro",Conciliación!$U$8:$U$114,$A15) | F15: =COUNTIFS(Conciliación!$AJ$8:$AJ$114,"Cobro",Conciliación!$U$8:$U$114,$A15)
A16: Comisiones | B16: =SUMIFS(Conciliación!$X$8:$X$114,Conciliación!$AJ$8:$AJ$114,"Cobro",Conciliación!$U$8:$U$114,$A16) | C16: =SUMIFS(Conciliación!$Y$8:$Y$114,Conciliación!$AJ$8:$AJ$114,"Cobro",Conciliación!$U$8:$U$114,$A16) | D16: =SUMIFS(Conciliación!$Z$8:$Z$114,Conciliación!$AJ$8:$AJ$114,"Cobro",Conciliación!$U$8:$U$114,$A16) | E16: =SUMIFS(Conciliación!$AA$8:$AA$114,Conciliación!$AJ$8:$AJ$114,"Cobro",Conciliación!$U$8:$U$114,$A16) | F16: =COUNTIFS(Conciliación!$AJ$8:$AJ$114,"Cobro",Conciliación!$U$8:$U$114,$A16)
A17: Otra retención | B17: =SUMIFS(Conciliación!$X$8:$X$114,Conciliación!$AJ$8:$AJ$114,"Cobro",Conciliación!$U$8:$U$114,$A17) | C17: =SUMIFS(Conciliación!$Y$8:$Y$114,Conciliación!$AJ$8:$AJ$114,"Cobro",Conciliación!$U$8:$U$114,$A17) | D17: =SUMIFS(Conciliación!$Z$8:$Z$114,Conciliación!$AJ$8:$AJ$114,"Cobro",Conciliación!$U$8:$U$114,$A17) | E17: =SUMIFS(Conciliación!$AA$8:$AA$114,Conciliación!$AJ$8:$AJ$114,"Cobro",Conciliación!$U$8:$U$114,$A17) | F17: =COUNTIFS(Conciliación!$AJ$8:$AJ$114,"Cobro",Conciliación!$U$8:$U$114,$A17)
A18: Total | B18: =SUM(B9:B17) | C18: =SUM(C9:C17) | D18: =SUM(D9:D17) | E18: =SUM(E9:E17) | F18: =SUM(F9:F17)
A21: Pagos a proveedores: IVA acreditable pagado
A22: Tipo de retención | B22: Base | C22: IVA | D22: IVA retenido | E22: ISR retenido | F22: Renglones
A23: Sin retención | B23: =SUMIFS(Conciliación!$X$8:$X$114,Conciliación!$AJ$8:$AJ$114,"Pago",Conciliación!$U$8:$U$114,$A23) | C23: =SUMIFS(Conciliación!$Y$8:$Y$114,Conciliación!$AJ$8:$AJ$114,"Pago",Conciliación!$U$8:$U$114,$A23) | D23: =SUMIFS(Conciliación!$Z$8:$Z$114,Conciliación!$AJ$8:$AJ$114,"Pago",Conciliación!$U$8:$U$114,$A23) | E23: =SUMIFS(Conciliación!$AA$8:$AA$114,Conciliación!$AJ$8:$AJ$114,"Pago",Conciliación!$U$8:$U$114,$A23) | F23: =COUNTIFS(Conciliación!$AJ$8:$AJ$114,"Pago",Conciliación!$U$8:$U$114,$A23)
A24: Honorarios | B24: =SUMIFS(Conciliación!$X$8:$X$114,Conciliación!$AJ$8:$AJ$114,"Pago",Conciliación!$U$8:$U$114,$A24) | C24: =SUMIFS(Conciliación!$Y$8:$Y$114,Conciliación!$AJ$8:$AJ$114,"Pago",Conciliación!$U$8:$U$114,$A24) | D24: =SUMIFS(Conciliación!$Z$8:$Z$114,Conciliación!$AJ$8:$AJ$114,"Pago",Conciliación!$U$8:$U$114,$A24) | E24: =SUMIFS(Conciliación!$AA$8:$AA$114,Conciliación!$AJ$8:$AJ$114,"Pago",Conciliación!$U$8:$U$114,$A24) | F24: =COUNTIFS(Conciliación!$AJ$8:$AJ$114,"Pago",Conciliación!$U$8:$U$114,$A24)
A25: Arrendamiento | B25: =SUMIFS(Conciliación!$X$8:$X$114,Conciliación!$AJ$8:$AJ$114,"Pago",Conciliación!$U$8:$U$114,$A25) | C25: =SUMIFS(Conciliación!$Y$8:$Y$114,Conciliación!$AJ$8:$AJ$114,"Pago",Conciliación!$U$8:$U$114,$A25) | D25: =SUMIFS(Conciliación!$Z$8:$Z$114,Conciliación!$AJ$8:$AJ$114,"Pago",Conciliación!$U$8:$U$114,$A25) | E25: =SUMIFS(Conciliación!$AA$8:$AA$114,Conciliación!$AJ$8:$AJ$114,"Pago",Conciliación!$U$8:$U$114,$A25) | F25: =COUNTIFS(Conciliación!$AJ$8:$AJ$114,"Pago",Conciliación!$U$8:$U$114,$A25)
A26: RESICO actividad empresarial | B26: =SUMIFS(Conciliación!$X$8:$X$114,Conciliación!$AJ$8:$AJ$114,"Pago",Conciliación!$U$8:$U$114,$A26) | C26: =SUMIFS(Conciliación!$Y$8:$Y$114,Conciliación!$AJ$8:$AJ$114,"Pago",Conciliación!$U$8:$U$114,$A26) | D26: =SUMIFS(Conciliación!$Z$8:$Z$114,Conciliación!$AJ$8:$AJ$114,"Pago",Conciliación!$U$8:$U$114,$A26) | E26: =SUMIFS(Conciliación!$AA$8:$AA$114,Conciliación!$AJ$8:$AJ$114,"Pago",Conciliación!$U$8:$U$114,$A26) | F26: =COUNTIFS(Conciliación!$AJ$8:$AJ$114,"Pago",Conciliación!$U$8:$U$114,$A26)
A27: RESICO honorarios | B27: =SUMIFS(Conciliación!$X$8:$X$114,Conciliación!$AJ$8:$AJ$114,"Pago",Conciliación!$U$8:$U$114,$A27) | C27: =SUMIFS(Conciliación!$Y$8:$Y$114,Conciliación!$AJ$8:$AJ$114,"Pago",Conciliación!$U$8:$U$114,$A27) | D27: =SUMIFS(Conciliación!$Z$8:$Z$114,Conciliación!$AJ$8:$AJ$114,"Pago",Conciliación!$U$8:$U$114,$A27) | E27: =SUMIFS(Conciliación!$AA$8:$AA$114,Conciliación!$AJ$8:$AJ$114,"Pago",Conciliación!$U$8:$U$114,$A27) | F27: =COUNTIFS(Conciliación!$AJ$8:$AJ$114,"Pago",Conciliación!$U$8:$U$114,$A27)
A28: RESICO arrendamiento | B28: =SUMIFS(Conciliación!$X$8:$X$114,Conciliación!$AJ$8:$AJ$114,"Pago",Conciliación!$U$8:$U$114,$A28) | C28: =SUMIFS(Conciliación!$Y$8:$Y$114,Conciliación!$AJ$8:$AJ$114,"Pago",Conciliación!$U$8:$U$114,$A28) | D28: =SUMIFS(Conciliación!$Z$8:$Z$114,Conciliación!$AJ$8:$AJ$114,"Pago",Conciliación!$U$8:$U$114,$A28) | E28: =SUMIFS(Conciliación!$AA$8:$AA$114,Conciliación!$AJ$8:$AJ$114,"Pago",Conciliación!$U$8:$U$114,$A28) | F28: =COUNTIFS(Conciliación!$AJ$8:$AJ$114,"Pago",Conciliación!$U$8:$U$114,$A28)
A29: Fletes | B29: =SUMIFS(Conciliación!$X$8:$X$114,Conciliación!$AJ$8:$AJ$114,"Pago",Conciliación!$U$8:$U$114,$A29) | C29: =SUMIFS(Conciliación!$Y$8:$Y$114,Conciliación!$AJ$8:$AJ$114,"Pago",Conciliación!$U$8:$U$114,$A29) | D29: =SUMIFS(Conciliación!$Z$8:$Z$114,Conciliación!$AJ$8:$AJ$114,"Pago",Conciliación!$U$8:$U$114,$A29) | E29: =SUMIFS(Conciliación!$AA$8:$AA$114,Conciliación!$AJ$8:$AJ$114,"Pago",Conciliación!$U$8:$U$114,$A29) | F29: =COUNTIFS(Conciliación!$AJ$8:$AJ$114,"Pago",Conciliación!$U$8:$U$114,$A29)
A30: Comisiones | B30: =SUMIFS(Conciliación!$X$8:$X$114,Conciliación!$AJ$8:$AJ$114,"Pago",Conciliación!$U$8:$U$114,$A30) | C30: =SUMIFS(Conciliación!$Y$8:$Y$114,Conciliación!$AJ$8:$AJ$114,"Pago",Conciliación!$U$8:$U$114,$A30) | D30: =SUMIFS(Conciliación!$Z$8:$Z$114,Conciliación!$AJ$8:$AJ$114,"Pago",Conciliación!$U$8:$U$114,$A30) | E30: =SUMIFS(Conciliación!$AA$8:$AA$114,Conciliación!$AJ$8:$AJ$114,"Pago",Conciliación!$U$8:$U$114,$A30) | F30: =COUNTIFS(Conciliación!$AJ$8:$AJ$114,"Pago",Conciliación!$U$8:$U$114,$A30)
A31: Otra retención | B31: =SUMIFS(Conciliación!$X$8:$X$114,Conciliación!$AJ$8:$AJ$114,"Pago",Conciliación!$U$8:$U$114,$A31) | C31: =SUMIFS(Conciliación!$Y$8:$Y$114,Conciliación!$AJ$8:$AJ$114,"Pago",Conciliación!$U$8:$U$114,$A31) | D31: =SUMIFS(Conciliación!$Z$8:$Z$114,Conciliación!$AJ$8:$AJ$114,"Pago",Conciliación!$U$8:$U$114,$A31) | E31: =SUMIFS(Conciliación!$AA$8:$AA$114,Conciliación!$AJ$8:$AJ$114,"Pago",Conciliación!$U$8:$U$114,$A31) | F31: =COUNTIFS(Conciliación!$AJ$8:$AJ$114,"Pago",Conciliación!$U$8:$U$114,$A31)
A32: Total | B32: =SUM(B23:B31) | C32: =SUM(C23:C31) | D32: =SUM(D23:D31) | E32: =SUM(E23:E31) | F32: =SUM(F23:F31)
A35: Cuadre del flujo contra el banco
A36: Concepto | B36: Cobros | C36: Pagos
A37: Amparado con CFDI | B37: =SUMIFS(Conciliación!$W$8:$W$114,Conciliación!$AJ$8:$AJ$114,"Cobro",Conciliación!$O$8:$O$114,"?*") | C37: =SUMIFS(Conciliación!$W$8:$W$114,Conciliación!$AJ$8:$AJ$114,"Pago",Conciliación!$O$8:$O$114,"?*")
A38: No requiere CFDI individual | B38: =SUMIFS(Conciliación!$W$8:$W$114,Conciliación!$AJ$8:$AJ$114,"Cobro",Conciliación!$N$8:$N$114,"No requiere CFDI") | C38: =SUMIFS(Conciliación!$W$8:$W$114,Conciliación!$AJ$8:$AJ$114,"Pago",Conciliación!$N$8:$N$114,"No requiere CFDI")
A39: Sin CFDI (no identificado) | B39: =SUMIFS(Conciliación!$W$8:$W$114,Conciliación!$AJ$8:$AJ$114,"Cobro",Conciliación!$N$8:$N$114,"Sin CFDI") | C39: =SUMIFS(Conciliación!$W$8:$W$114,Conciliación!$AJ$8:$AJ$114,"Pago",Conciliación!$N$8:$N$114,"Sin CFDI")
A40: Excedente de movimientos en revisión | B40: =SUMIFS(Conciliación!$AK$8:$AK$114,Conciliación!$AJ$8:$AJ$114,"Cobro") | C40: =SUMIFS(Conciliación!$AK$8:$AK$114,Conciliación!$AJ$8:$AJ$114,"Pago")
A41: Total explicado | B41: =SUM(B37:B40) | C41: =SUM(C37:C40)
A42: Según estado de cuenta | B42: ='Estado de cuenta'!L17 | C42: ='Estado de cuenta'!L18
A43: Diferencia | B43: =ROUND(B41-B42,2) | C43: =ROUND(C41-C42,2)
A44: Si la diferencia es cero, todo peso que entró o salió del banco quedó explicado en la conciliación.

Sheet Previo
C1: MLR CONSULTORES
C2: Previo de impuestos del mes
C3: <Empresa> · <Mes Año>
A5: Cálculo preliminar para enviar al cliente. Se alimenta del Desglose fiscal; las celdas en azul claro se capturan a mano.
C7: Cálculo de impuestos correspondientes al mes de <Mes Año>
E9: Importe | F9: A pagar
C11: ISR retenciones
C12: ISR retenido por salarios | E12: 0 | H12: Captura el ISR de la nómina del mes.
C13: ISR retenido por arrendamiento | E13: =ROUNDDOWN((SUMIFS('Desglose fiscal'!E23:E31,'Desglose fiscal'!A23:A31,"Arrendamiento"))+0.49,0)
C14: ISR retenido a RESICO | E14: =ROUNDDOWN((SUMIFS('Desglose fiscal'!E23:E31,'Desglose fiscal'!A23:A31,"RESICO actividad empresarial")+SUMIFS('Desglose fiscal'!E23:E31,'Desglose fiscal'!A23:A31,"RESICO honorarios")+SUMIFS('Desglose fiscal'!E23:E31,'Desglose fiscal'!A23:A31,"RESICO arrendamiento"))+0.49,0)
C15: ISR retenido por servicios profesionales | E15: =ROUNDDOWN((SUMIFS('Desglose fiscal'!E23:E31,'Desglose fiscal'!A23:A31,"Honorarios"))+0.49,0)
C16: Total ISR retenido por pagar | F16: =SUM(E12:E15)
C18: ISR propio de la persona moral
C19: ISR del pago provisional | E19: 0 | H19: Si es el primer ejercicio: sin pago provisional según el art. 14 de la LISR. Por confirmar.
C20: (-) Pagos provisionales anteriores | E20: 0
C21: (+) Recargos y actualización | E21: 0
C22: Total ISR persona moral por pagar | F22: =MAX(0,E19-E20+E21)
C24: IVA (Impuesto al Valor Agregado)
C25: IVA cobrado 16% | E25: =ROUNDDOWN(('Desglose fiscal'!C18)+0.49,0)
C26: (-) IVA pagado 16% | E26: =ROUNDDOWN(('Desglose fiscal'!C32)+0.49,0)
C27: (-) Aplicación de saldo a favor de meses anteriores | E27: 0 | H27: Captura el remanente que vas a aplicar.
C28: Total IVA por pagar | F28: =MAX(0,E25-E26-E27)
C29: IVA a favor del mes | F29: =MAX(0,E26+E27-E25)
C31: IVA retenido
C32: IVA retenido a proveedores | E32: =ROUNDDOWN(('Desglose fiscal'!D32)+0.49,0)
C33: Total IVA retenido por pagar | F33: =E32
C36: TOTAL A PAGAR | F36: =F16+F22+F28+F33
C38: Los importes se ajustan a pesos como indica el art. 20 del CFF: de 1 a 50 centavos bajan y de 51 a 99 suben. Cifras preliminares sujetas a la revisión del papel de trabajo.
C41: Comparativo contra el previo manual del analista (etapa de pruebas)
C42: Concepto | E42: Manual | F42: Este libro | G42: Odoo | H42: Diferencia libro vs manual
C43: IVA cobrado 16% | F43: =E25 | G43: ='Impuestos vs Odoo'!D10 | H43: =F43-E43
C44: IVA pagado 16% | F44: =E26 | G44: ='Impuestos vs Odoo'!D9 | H44: =F44-E44
C45: IVA retenido | F45: =E32 | H45: =F45-E45
C46: ISR retenido (servicios profesionales y RESICO) | F46: =E14+E15 | H46: =F46-E46
C47: Fuente de la columna Manual: previo del analista. Se borra al terminar las pruebas.

Sheet Estado de cuenta
C1: MLR CONSULTORES
C2: Estado de cuenta bancario
C3: <Empresa> · <Mes Año>
A5: Leído directamente del PDF del banco. Los movimientos van a la izquierda y la carátula a la derecha; el control de saldos compara ambos.
A7: Partida | B7: Fecha | C7: Código | D7: Descripción completa | E7: Cargos | F7: Abonos | G7: Saldo | K7: CARÁTULA DEL ESTADO DE CUENTA
G8: =$L$16+F8-E8 | K8: Banco
G9: =G8+F9-E9 | K9: Producto
G10: =G9+F10-E10 | K10: Titular
G11: =G10+F11-E11 | K11: RFC
G12: =G11+F12-E12 | K12: Número de cuenta
G13: =G12+F13-E13 | K13: CLABE
G14: =G13+F14-E14 | K14: Número de cliente
G15: =G14+F15-E15 | K15: Sucursal
G16: =G15+F16-E16 | K16: Saldo inicial
G17: =G16+F17-E17 | K17: Depósitos / abonos (+)
G18: =G17+F18-E18 | K18: Retiros / cargos (-)
G19: =G18+F19-E19 | K19: Saldo final
G20: =G19+F20-E20 | K20: Saldo promedio
G21: =G20+F21-E21 | K21: Total de comisiones del periodo
G22: =G21+F22-E22
G23: =G22+F23-E23 | K23: CONTROL: LO LEÍDO CONTRA LA CARÁTULA
G24: =G23+F24-E24 | K24: Abonos leídos | L24: =SUM(F8:F114) | M24: =COUNT(F8:F114)
G25: =G24+F25-E25 | K25: Cargos leídos | L25: =SUM(E8:E114) | M25: =COUNT(E8:E114)
G26: =G25+F26-E26 | K26: Saldo final calculado | L26: =G114
G27: =G26+F27-E27 | K27: Diferencia contra la carátula | L27: =ROUND(L26-L19,2)+ROUND(L24-L17,2)+ROUND(L25-L18,2) | M27: =(M24-M17)+(M25-M18)
G28: =G27+F28-E28 | K28: =IF(AND(L27=0,M27=0),"El PDF quedó leído completo y cuadra al centavo.","Hay diferencia: revisa la lectura del PDF.")
G29: =G28+F29-E29
G30: =G29+F30-E30
G31: =G30+F31-E31
G32: =G31+F32-E32
G33: =G32+F33-E33
G34: =G33+F34-E34
G35: =G34+F35-E35
G36: =G35+F36-E36
G37: =G36+F37-E37
G38: =G37+F38-E38
G39: =G38+F39-E39
G40: =G39+F40-E40
... G114: =G113+F114-E114

Sheet Auxiliar Odoo
C1: MLR CONSULTORES
C2: Auxiliar de bancos en Odoo
C3: <Empresa> · <Mes Año>
A5: Exportado de Odoo, diario <Diario>. Se usa tal como llegó; no se edita.
A7: Renglón | B7: Fecha | C7: Asiento | D7: Concepto en Odoo | E7: Contacto | F7: Cargos | G7: Abonos | H7: Saldo | J7: Saldo final según Odoo
H8: =$J$12+G8-F8 | J8: =H114
H9: =H8+G9-F9 | J9: Diferencia contra el banco
H10: =H9+G10-F10 | J10: =ROUND(J8-'Estado de cuenta'!L19,2)
H11: =H10+G11-F11 | J11: Saldo inicial en Odoo
H12: =H11+G12-F12
H13: =H12+G13-F13 | J13: Tomado del auxiliar exportado de Odoo.
H14: =H13+G14-F14
H15: =H14+G15-F15
H16: =H15+G16-F16
H17: =H16+G17-F17
H18: =H17+G18-F18
H19: =H18+G19-F19
H20: =H19+G20-F20
H21: =H20+G21-F21
H22: =H21+G22-F22
H23: =H22+G23-F23
H24: =H23+G24-F24
H25: =H24+G25-F25
... H114: =H113+G114-F114

Sheet Reglas
C1: MLR CONSULTORES
C2: Reglas de la conciliación
C3: <Empresa> · <Mes Año>
A5: Las celdas en azul claro son las únicas que se editan. Si cambias una tolerancia, todo el libro se recalcula.
B7: Diferencia máxima de importe (pesos) | C7: 1
B8: Desfase máximo de fecha (días) | C8: 3
B10: Estatus de cada renglón
B11: Conciliado | C11: Banco, Odoo y CFDI coinciden dentro de las tolerancias. Incluye comisiones, impuestos y nómina, que no requieren CFDI individual.
B12: Conciliado (validar) | C12: Un pago que cubre varias facturas, varias facturas en un pago, o un cobro parcial de una factura.
B13: Conciliado (revisar) | C13: Tiene pareja, pero la diferencia pasa de la tolerancia de importe o el desfase pasa de la tolerancia de días.
B14: No identificado | C14: Está en el banco y no en Odoo, está en Odoo y no en el banco, o no tiene CFDI que lo respalde.
B17: Retenciones cuando una persona moral paga a una persona física
B18: Tipo de proveedor | C18: ISR retenido | D18: IVA retenido | E18: Color
B19: Honorarios (servicios profesionales) | C19: 10% | D19: 2/3 del IVA | E19: Honorarios
B20: Arrendamiento | C20: 10% | D20: 2/3 del IVA | E20: Arrendamiento
B21: RESICO con actividad empresarial | C21: 1.25% | D21: No hay | E21: RESICO actividad empresarial
B22: RESICO con honorarios | C22: 1.25% | D22: 2/3 del IVA | E22: RESICO honorarios
B23: RESICO con arrendamiento | C23: 1.25% | D23: 2/3 del IVA | E23: RESICO arrendamiento
B24: Fletes (autotransporte de bienes) | C24: No hay | D24: 4% (art. 1-A, fr. II, inc. c, LIVA): por confirmar criterio | E24: Fletes
B25: Comisiones | C25: No hay | D25: 2/3 del IVA (art. 3, fr. I, RLIVA): por confirmar criterio | E25: Comisiones
B26: Actividad empresarial (no RESICO) | C26: No hay | D26: No hay | E26: Sin retención
B28: Fuente: tabla de retenciones de CONTPAQi compartida por el analista, con dos ajustes (fletes y comisiones) pendientes de criterio. La retención de IVA del 6% no se usa. Una factura sin retención que por su concepto debió llevarla se marca como alerta.
B31: Palabras con que se lee el concepto de la factura
B32: Arrendamiento | C32: renta, arrend, alquiler
B33: Fletes | C33: flete, autotransporte, transporte de carga, maniobra
B34: Comisiones | C34: comision
B35: Honorarios | C35: honorario, servicios profesionales, consultoria, asesoria, contable, juridic, auditoria
